psycopg2_wrapper/__init__.py
psycopg2_wrapper/database.py
psycopg2_wrapper/validator.py
psycopg2_wrapper-1.0.dist-info/LICENSE
psycopg2_wrapper-1.0.dist-info/METADATA
psycopg2_wrapper-1.0.dist-info/WHEEL
psycopg2_wrapper-1.0.dist-info/top_level.txt
psycopg2_wrapper-1.0.dist-info/RECORD
