Metadata-Version: 2.1
Name: psycopg2-wrapper
Version: 1.0
Summary: Simple wrapper for executing commands and queries
Home-page: https://github.com/atakanozguryildiz/psycopg2-wrapper
Author: Atakan Ozgur Yildiz
Author-email: atakanozguryildiz@gmail.com
License: UNKNOWN
Platform: UNKNOWN
Classifier: Programming Language :: Python :: 3
Classifier: License :: OSI Approved :: MIT License
Classifier: Operating System :: OS Independent
Requires-Python: >=3.6
Requires-Dist: psycopg2 (==2.8.4)
